ldimbenchmark/__init__.py
ldimbenchmark/benchmark/__init__.py
ldimbenchmark/benchmark/benchmark.py
ldimbenchmark/benchmark/results.py
ldimbenchmark/benchmark/runners/BaseMethodRunner.py
ldimbenchmark/benchmark/runners/DockerMethodRunner.py
ldimbenchmark/benchmark/runners/FileMethodRunner.py
ldimbenchmark/benchmark/runners/LocalMethodRunner.py
ldimbenchmark/benchmark/runners/__init__.py
ldimbenchmark/benchmark_complexity.py
ldimbenchmark/benchmark_evaluation.py
ldimbenchmark/classes/BenchmarkData.py
ldimbenchmark/classes/BenchmarkLeakageResult.py
ldimbenchmark/classes/LDIMMethodBase.py
ldimbenchmark/classes/MethodMetadata.py
ldimbenchmark/classes/__init__.py
ldimbenchmark/cli.py
ldimbenchmark/constants.py
ldimbenchmark/datasets/__init__.py
ldimbenchmark/datasets/analysis.py
ldimbenchmark/datasets/classes.py
ldimbenchmark/datasets/derivation.py
ldimbenchmark/datasets/derivation_show.py
ldimbenchmark/datasets/library.py
ldimbenchmark/datasets/loaders/__init__.py
ldimbenchmark/datasets/loaders/load_battledim.py
ldimbenchmark/datasets/loaders/load_dataset_base.py
ldimbenchmark/evaluation/__init__.py
ldimbenchmark/evaluation/sensitivity.py
ldimbenchmark/evaluation_metrics/__init__.py
ldimbenchmark/generator/__init__.py
ldimbenchmark/generator/dataset_generator.py
ldimbenchmark/generator/poulakis_network.py
ldimbenchmark/methods/__init__.py
ldimbenchmark/methods/dualmethod.py
ldimbenchmark/methods/lila.py
ldimbenchmark/methods/mnf.py
ldimbenchmark/methods/null.py
ldimbenchmark/methods/random.py
ldimbenchmark/methods/test_complexity_constant.py
ldimbenchmark/methods/test_complexity_exponential.py
ldimbenchmark/methods/test_complexity_linear.py
ldimbenchmark/methods/test_complexity_polynomial.py
ldimbenchmark/methods/utils/__init__.py
ldimbenchmark/methods/utils/cusum.py
ldimbenchmark/utilities.py
ldimbenchmark-0.2.67.dist-info/entry_points.txt
ldimbenchmark-0.2.67.dist-info/WHEEL
ldimbenchmark-0.2.67.dist-info/METADATA
ldimbenchmark-0.2.67.dist-info/RECORD
