Metadata-Version: 2.1
Name: ldimbenchmark
Version: 0.2.67
Summary: 
Author: DanielHabenicht
Author-email: daniel-habenicht@outlook.de
Requires-Python: >=3.8,<4
Classifier: Programming Language :: Python :: 3
Classifier: Programming Language :: Python :: 3.8
Classifier: Programming Language :: Python :: 3.9
Classifier: Programming Language :: Python :: 3.10
Classifier: Programming Language :: Python :: 3.11
Requires-Dist: big-o-latest (>=0.10.3,<0.11.0)
Requires-Dist: click (>=8.1.3,<9.0.0)
Requires-Dist: docker (>=6.0.1,<7.0.0)
Requires-Dist: enlighten (>=1.11.2,<2.0.0)
Requires-Dist: jinja2 (>=3.1.2,<4.0.0)
Requires-Dist: more-itertools (>=9.1.0,<10.0.0)
Requires-Dist: numpy (>=1.23.5,<2.0.0)
Requires-Dist: pandas (>=1.5.2,<2.0.0)
Requires-Dist: paramiko (>=3.0.0,<4.0.0)
Requires-Dist: pydantic (>=1.10.2,<2.0.0)
Requires-Dist: python-semantic-release (>=7.33.2,<8.0.0)
Requires-Dist: pyyaml (>=6.0,<7.0)
Requires-Dist: scikit-learn (>=1.1.3,<2.0.0)
Requires-Dist: seaborn (>=0.12.2,<0.13.0)
Requires-Dist: sqlalchemy (<2)
Requires-Dist: sympy (>=1.11.1,<2.0.0)
Requires-Dist: tables (>=3.8.0,<4.0.0)
Requires-Dist: tabulate (>=0.9.0,<0.10.0)
Requires-Dist: wntr (>=0.5.0,<0.6.0)
